task_handlers/__init__.py
task_handlers/docker_task_handler.py
task_handlers/ecs_task_handler.py
task_handlers/test_task_handler.py
tmgr/__init__.py
tmgr/__main__.py
tmgr/configuration_helper.py
tmgr/db_base.py
tmgr/db_helper.py
tmgr/db_mgr.py
tmgr/env_loader.py
tmgr/global_config.py
tmgr/periodic_task.py
tmgr/task_db.py
tmgr/task_handler_interface.py
tmgr/task_loader.py
tmgr/tmgr.py
tmgr/tools.py
tmgr/version.py
tmgr/enums/__init__.py
tmgr/enums/enum_base.py
tmgr/enums/lit_enum.py
tmgr/enums/task_status_enum.py
tmgr/log_handlers/__init__.py
tmgr/log_handlers/custom_logger.py
tmgr/log_handlers/log_custom_formater.py
tmgr/log_handlers/origin_adapter.py
tmgr/log_handlers/origin_filter.py
tmgr/log_handlers/postgres_handler.py
tmgr/log_handlers/rotating_file_handler.py
tmgr/log_handlers/sqllite_handler.py
tmgr/model/__init__.py
tmgr/model/base_manager.py
tmgr/model/config.py
tmgr/model/task.py
tmgr/model/task_dep.py
simple_task_manager-1.5.37.dist-info/LICENSE
simple_task_manager-1.5.37.dist-info/METADATA
simple_task_manager-1.5.37.dist-info/WHEEL
simple_task_manager-1.5.37.dist-info/top_level.txt
simple_task_manager-1.5.37.dist-info/RECORD
