Metadata-Version: 2.1
Name: simple_task_manager
Version: 1.5.37
Summary: Simple task manager to handle execution of tasks in AWS docker or any system. It use a handler that can be loaded dynamically.
Home-page: https://github.com/Fran-4c4/staskmgr
Author: Francisco R. Moreno Santana
Author-email: franrms@gmail.com
License: Apache License 2.0
Project-URL: Bug Tracker, https://github.com/Fran-4c4/staskmgr/issues
Project-URL: Source Code, https://github.com/Fran-4c4/staskmgr
Keywords: attr: tmgr.__keywords__
Classifier: Programming Language :: Python :: 3.7
Classifier: Programming Language :: Python :: 3.8
Classifier: Programming Language :: Python :: 3.9
Classifier: Programming Language :: Python :: 3.10
Classifier: Programming Language :: Python :: 3.11
Classifier: Programming Language :: Python :: 3 :: Only
Classifier: Topic :: System :: Distributed Computing
Classifier: Operating System :: OS Independent
Requires-Python: >=3.7
License-File: LICENSE
Requires-Dist: SQLAlchemy>=2.0.0
Requires-Dist: python-dotenv
Requires-Dist: psycopg[binary]
Requires-Dist: psycopg-pool
Requires-Dist: docker
